{
  "key": "wizard",
  "label": "Wizard Jason",
  "author": "NPCJason",
  "description": "A robe-and-stars variant for maximum desktop spellcasting.",
  "version": "1.2",
  "char_map": {
    "T": "Z",
    "P": "D",
    "B": "L",
    "O": "L"
  },
  "palette": {
    "Z": "#6857d4",
    "D": "#3f4b74",
    "L": "#ffd166"
  },
  "tray": {
    "hair": "#4a3728",
    "body": "#6857d4",
    "legs": "#3f4b74"
  },
  "overlay": [
    ".....ZZZZZ......",
    "....ZZZZZZZ.....",
    "...ZZZZLZZZZ....",
    "....ZZZZZZZZ....",
    ".....ZZZZZZ.....",
    "................",
    "................",
    "................",
    "................",
    "................",
    "................",
    "................",
    "................",
    "................",
    "................",
    "................",
    "................",
    "................",
    "................",
    "................"
  ]
}
